pagetree/__init__.py
pagetree/admin.py
pagetree/helpers.py
pagetree/models.py
pagetree/urls.py
pagetree/views.py
pagetree/media/css/pagetree.css
pagetree/migrations/0001_initial.py
pagetree/migrations/0002_alter_hierarchy_base_url.py
pagetree/migrations/__init__.py
pagetree/templates/__init__.py
pagetree/templates/admin/__init__.py
pagetree/templates/admin/pagetree/__init__.py
pagetree/templates/admin/pagetree/pageblock/__init__.py
pagetree/templates/admin/pagetree/pageblock/add_pageblock.html
pagetree/templates/admin/pagetree/pageblock/edit_pageblock.html
pagetree/templates/admin/pagetree/pageblock/edit_inline/__init__.py
pagetree/templates/admin/pagetree/pageblock/edit_inline/stacked.html
pagetree/templates/admin/pagetree/section/__init__.py
pagetree/templates/admin/pagetree/section/add_section.html
pagetree/templates/admin/pagetree/section/change_form.html
pagetree/templates/admin/pagetree/section/change_list.html
pagetree/templates/admin/pagetree/sectionchildren/__init__.py
pagetree/templates/admin/pagetree/sectionchildren/edit_inline/__init__.py
pagetree/templates/admin/pagetree/sectionchildren/edit_inline/stacked.html
pagetree/templatetags/__init__.py
pagetree/templatetags/getroot.py
pagetree/templatetags/render.py
pagetree-0.7.5.dist-info/METADATA
pagetree-0.7.5.dist-info/WHEEL
pagetree-0.7.5.dist-info/top_level.txt
pagetree-0.7.5.dist-info/RECORD
