Metadata-Version: 2.1
Name: pagetree
Version: 0.7.5
Summary: Tree of Pages helper application
Home-page: https://github.com/ccnmtl/pagetree
Author: Anders Pearson
Author-email: ctl-dev@columbia.edu
License: BSD
Platform: any
Requires-Dist: django
